{
    "model": "llama3",
    "task": "sentiment_yelp",
    "k": 62,
    "heads": [
        {
            "layer": 10,
            "head": 23,
            "score": 0.9631552635406961
        },
        {
            "layer": 5,
            "head": 10,
            "score": 0.8924782896528438
        },
        {
            "layer": 12,
            "head": 15,
            "score": 0.8041255221683152
        },
        {
            "layer": 10,
            "head": 1,
            "score": 0.7284220168176962
        },
        {
            "layer": 12,
            "head": 13,
            "score": 0.7026072389313153
        },
        {
            "layer": 10,
            "head": 20,
            "score": 0.634027400947347
        },
        {
            "layer": 2,
            "head": 26,
            "score": 0.5082705610868882
        },
        {
            "layer": 12,
            "head": 2,
            "score": 0.4933667683935895
        },
        {
            "layer": 15,
            "head": 12,
            "score": 0.45878780484959786
        },
        {
            "layer": 13,
            "head": 20,
            "score": 0.45831797667303864
        },
        {
            "layer": 7,
            "head": 5,
            "score": 0.4175481119630288
        },
        {
            "layer": 5,
            "head": 9,
            "score": 0.39154557990176336
        },
        {
            "layer": 11,
            "head": 22,
            "score": 0.35448627905654057
        },
        {
            "layer": 14,
            "head": 21,
            "score": 0.31948355030344455
        },
        {
            "layer": 13,
            "head": 21,
            "score": 0.3041797617250787
        },
        {
            "layer": 2,
            "head": 20,
            "score": 0.2989114146033416
        },
        {
            "layer": 14,
            "head": 20,
            "score": 0.29522259761484304
        },
        {
            "layer": 5,
            "head": 11,
            "score": 0.28942873549400544
        },
        {
            "layer": 13,
            "head": 2,
            "score": 0.2812411991632258
        },
        {
            "layer": 14,
            "head": 22,
            "score": 0.2517654091233806
        },
        {
            "layer": 11,
            "head": 7,
            "score": 0.2514473816703017
        },
        {
            "layer": 14,
            "head": 15,
            "score": 0.24893708945232995
        },
        {
            "layer": 15,
            "head": 20,
            "score": 0.24626242259175193
        },
        {
            "layer": 11,
            "head": 4,
            "score": 0.24308551931563688
        },
        {
            "layer": 10,
            "head": 13,
            "score": 0.23912486530916424
        },
        {
            "layer": 10,
            "head": 21,
            "score": 0.2363784446628118
        },
        {
            "layer": 14,
            "head": 29,
            "score": 0.2252769737067271
        },
        {
            "layer": 12,
            "head": 29,
            "score": 0.22297196251777363
        },
        {
            "layer": 14,
            "head": 14,
            "score": 0.22167526824133738
        },
        {
            "layer": 15,
            "head": 30,
            "score": 0.2155418274924159
        },
        {
            "layer": 14,
            "head": 9,
            "score": 0.21173121980201376
        },
        {
            "layer": 11,
            "head": 14,
            "score": 0.2109068040260855
        },
        {
            "layer": 12,
            "head": 14,
            "score": 0.2061470575697188
        },
        {
            "layer": 11,
            "head": 6,
            "score": 0.20224350221854234
        },
        {
            "layer": 11,
            "head": 20,
            "score": 0.20208872398908004
        },
        {
            "layer": 12,
            "head": 31,
            "score": 0.20179843678547793
        },
        {
            "layer": 12,
            "head": 12,
            "score": 0.20070538254055595
        },
        {
            "layer": 13,
            "head": 31,
            "score": 0.19444947691909892
        },
        {
            "layer": 11,
            "head": 27,
            "score": 0.18041907052262401
        },
        {
            "layer": 14,
            "head": 31,
            "score": 0.17939019731569047
        },
        {
            "layer": 14,
            "head": 12,
            "score": 0.17271172633508639
        },
        {
            "layer": 15,
            "head": 31,
            "score": 0.15882044235168366
        },
        {
            "layer": 13,
            "head": 0,
            "score": 0.148621985897878
        },
        {
            "layer": 14,
            "head": 2,
            "score": 0.14779154214133716
        },
        {
            "layer": 11,
            "head": 25,
            "score": 0.14577105481234587
        },
        {
            "layer": 11,
            "head": 13,
            "score": 0.14311368085386955
        },
        {
            "layer": 10,
            "head": 22,
            "score": 0.1425636984712007
        },
        {
            "layer": 15,
            "head": 7,
            "score": 0.13766069341051793
        },
        {
            "layer": 10,
            "head": 14,
            "score": 0.13648919244201815
        },
        {
            "layer": 15,
            "head": 4,
            "score": 0.13240034065722506
        },
        {
            "layer": 14,
            "head": 28,
            "score": 0.13237414186183669
        },
        {
            "layer": 14,
            "head": 30,
            "score": 0.131427062109911
        },
        {
            "layer": 15,
            "head": 29,
            "score": 0.13081937979868785
        },
        {
            "layer": 10,
            "head": 9,
            "score": 0.1305760283507787
        },
        {
            "layer": 14,
            "head": 3,
            "score": 0.12812891403659799
        },
        {
            "layer": 8,
            "head": 20,
            "score": 0.12665558843968475
        },
        {
            "layer": 11,
            "head": 12,
            "score": 0.11964975995467786
        },
        {
            "layer": 15,
            "head": 21,
            "score": 0.11896372299489318
        },
        {
            "layer": 14,
            "head": 11,
            "score": 0.11390991267577118
        },
        {
            "layer": 10,
            "head": 26,
            "score": 0.10864434543312812
        },
        {
            "layer": 7,
            "head": 6,
            "score": 0.10594579110834368
        },
        {
            "layer": 10,
            "head": 30,
            "score": 0.10034314318731123
        }
    ]
}